{
  "project_info": {
    "project_number": "776221043104",
    "firebase_url": "https://seg2505-lab5-da1d1.firebaseio.com",
    "project_id": "seg2505-lab5-da1d1",
    "storage_bucket": "seg2505-lab5-da1d1.appspot.com"
  },
  "client": [
    {
      "client_info": {
        "mobilesdk_app_id": "1:776221043104:android:253e212d26fa12e58a1cc5",
        "android_client_info": {
          "package_name": "com.example.seg2505_lab5"
        }
      },
      "oauth_client": [
        {
          "client_id": "776221043104-5k1v12sbuaa2kjco80fui29f9f4frdqq.apps.googleusercontent.com",
          "client_type": 3
        }
      ],
      "api_key": [
        {
          "current_key": "AIzaSyDAfrAo0wPWYZG830qMkW3eCI-eu_FUOTI"
        }
      ],
      "services": {
        "appinvite_service": {
          "other_platform_oauth_client": [
            {
              "client_id": "776221043104-5k1v12sbuaa2kjco80fui29f9f4frdqq.apps.googleusercontent.com",
              "client_type": 3
            }
          ]
        }
      }
    }
  ],
  "configuration_version": "1"
}